offsh_xxh-1.0.0.data/scripts/xxh
offsh_xxh-1.0.0.data/scripts/xxh.bash
offsh_xxh-1.0.0.data/scripts/xxh.xsh
offsh_xxh-1.0.0.data/scripts/xxh.zsh
xxh_xxh/__init__.py
xxh_xxh/config.xxhc
xxh_xxh/shell.py
xxh_xxh/xxh.bash
xxh_xxh/xxh.py
xxh_xxh/xxh.xsh
xxh_xxh/xxh.zsh
offsh_xxh-1.0.0.dist-info/LICENSE
offsh_xxh-1.0.0.dist-info/METADATA
offsh_xxh-1.0.0.dist-info/WHEEL
offsh_xxh-1.0.0.dist-info/top_level.txt
offsh_xxh-1.0.0.dist-info/RECORD
