Metadata-Version: 2.1
Name: offsh-xxh
Version: 1.0.0
Summary: Bring your favorite shell wherever you go through the ssh. This is a fork from https://github.com/xxh/xxh with some extra featured designed for https://github.com/offsh/offshell
Home-page: https://github.com/offsh/xxh
Author: offsh
Author-email: navarromoralesdev@gmail.com
License: BSD
Project-URL: Documentation, https://github.com/offsh/xxh/blob/master/README.md
Project-URL: Code, https://github.com/offsh/xxh
Project-URL: Issue tracker, https://github.com/offsh/xxh/issues
Platform: Unix-like
Classifier: Programming Language :: Python :: 3
Classifier: Programming Language :: Unix Shell
Classifier: Topic :: System :: Shells
Classifier: Topic :: System :: System Shells
Classifier: Topic :: Terminals
Classifier: Topic :: System :: Networking
Classifier: License :: OSI Approved :: BSD License
Requires-Python: >=3.6
Requires-Dist: pexpect (>=4.8.0)
Requires-Dist: pyyaml
